pyramis/__init__.py
pyramis/astro.py
pyramis/basic.py
pyramis/config_base.toml
pyramis/config_module.py
pyramis/core.py
pyramis/geometry.py
pyramis/halo.py
pyramis/hdf.py
pyramis/image.py
pyramis/io.py
pyramis/scripts/amr2hdf.py
pyramis/utils/__init__.py
pyramis/utils/arrayview.py
pyramis/utils/basic.py
pyramis/utils/fortranfile.py
pyramis/utils/hilbert3d.py
pyramis-0.1.10.dist-info/licenses/LICENSE
pyramis-0.1.10.dist-info/METADATA
pyramis-0.1.10.dist-info/WHEEL
pyramis-0.1.10.dist-info/top_level.txt
pyramis-0.1.10.dist-info/RECORD
