Metadata-Version: 2.4
Name: pyramis
Version: 0.1.10
Summary: A python-based ramses analyzer for minimalist
Author-email: San Han <san.han@iap.fr>
License: MIT License
Project-URL: Repository, https://github.com/sanhan/pyramis
Keywords: ramses
Requires-Python: >=3.11
License-File: LICENSE
Requires-Dist: h5py>=3.12.1
Requires-Dist: numpy>=1.26.4
Requires-Dist: scipy>=1.16.3
Requires-Dist: scikit-image>=0.21.0
Dynamic: license-file
